phibes/__init__.py
phibes/util.py
phibes/cli/__init__.py
phibes/cli/cli_config.py
phibes/cli/commands.py
phibes/cli/errors.py
phibes/cli/handlers.py
phibes/cli/lib.py
phibes/cli/options.py
phibes/cli/scripts.py
phibes/crypto/__init__.py
phibes/crypto/aes_cipher.py
phibes/crypto/crypt_aes_argon2.py
phibes/crypto/crypt_aes_ctr_sha.py
phibes/crypto/crypt_ifc.py
phibes/crypto/crypt_plain_plain.py
phibes/crypto/encrypt_aes.py
phibes/crypto/factory.py
phibes/crypto/hash_argon2.py
phibes/crypto/hash_pbkdf2.py
phibes/lib/__init__.py
phibes/lib/config.py
phibes/lib/errors.py
phibes/lib/phibes_file.py
phibes/lib/utils.py
phibes/lib/views.py
phibes/model/__init__.py
phibes/model/item.py
phibes/model/locker.py
phibes/model/model.py
phibes/storage/__init__.py
phibes/storage/file_storage.py
phibes/storage/memory_storage.py
phibes/storage/sqlite3_storage.py
phibes/storage/storage_impl.py
phibes/storage/types.py
Phibes-0.0.5.dist-info/LICENSE
Phibes-0.0.5.dist-info/METADATA
Phibes-0.0.5.dist-info/WHEEL
Phibes-0.0.5.dist-info/entry_points.txt
Phibes-0.0.5.dist-info/top_level.txt
Phibes-0.0.5.dist-info/RECORD
