Metadata-Version: 2.1
Name: Phibes
Version: 0.0.5
Summary: A basic encryption utility
Home-page: https://github.com/GlenRSmith/Phibes
Author: Glen R Smith
Author-email: phibes@smithsrock.com
License: LGPLv2+
Project-URL: Bug Tracker, https://github.com/GlenRSmith/Phibes/issues
Keywords: security,encryption
Platform: any
Classifier: Development Status :: 3 - Alpha
Classifier: Intended Audience :: Developers
Classifier: Programming Language :: Python :: 3
Classifier: Programming Language :: Python :: 3.8
Classifier: Programming Language :: Python :: 3.9
Classifier: Topic :: Software Development :: Libraries :: Python Modules
Classifier: License :: OSI Approved :: GNU Lesser General Public License v2 or later (LGPLv2+)
Classifier: Operating System :: OS Independent
Classifier: Topic :: Security :: Cryptography
Requires-Python: >=3.8
Requires-Dist: click (>=7.1.2)
Requires-Dist: pycryptodomex (==3.10.1)
Provides-Extra: develop
Requires-Dist: flake8 (>=3.9.0) ; extra == 'develop'
Requires-Dist: pytest (>=6.2.2) ; extra == 'develop'
Requires-Dist: pytest-datadir-ng (>=1.1.1) ; extra == 'develop'
Requires-Dist: pytest-cov (>=2.11.1) ; extra == 'develop'
Requires-Dist: twine (>=3.4.1) ; extra == 'develop'
